octopus_energy/__init__.py
octopus_energy/client.py
octopus_energy/exceptions.py
octopus_energy/mappers.py
octopus_energy/models.py
octopus_energy/rest_client.py
readme.md
octopus_energy-0.1.14.dist-info/LICENSE
octopus_energy-0.1.14.dist-info/WHEEL
octopus_energy-0.1.14.dist-info/METADATA
octopus_energy-0.1.14.dist-info/RECORD
