Metadata-Version: 2.1
Name: octopus-energy
Version: 0.1.14
Summary: Python client for the Octopus Energy RESTful API
Home-page: https://github.com/markallanson/octopus-energy
License: MIT
Author: Mark Allanson
Author-email: mark@allanson.org
Requires-Python: >=3.8,<4.0
Classifier: License :: OSI Approved :: MIT License
Classifier: Programming Language :: Python :: 3
Classifier: Programming Language :: Python :: 3.8
Classifier: Programming Language :: Python :: 3.9
Requires-Dist: aiohttp (>=3.7.1,<4.0.0)
Requires-Dist: furl (>=2.1.0,<3.0.0)
Requires-Dist: python-dateutil (>=2.8.1,<3.0.0)
